odoo/addons/stock_lot_production_date/README.rst
odoo/addons/stock_lot_production_date/__init__.py
odoo/addons/stock_lot_production_date/__manifest__.py
odoo/addons/stock_lot_production_date/i18n/it.po
odoo/addons/stock_lot_production_date/i18n/sl.po
odoo/addons/stock_lot_production_date/i18n/stock_lot_production_date.pot
odoo/addons/stock_lot_production_date/models/__init__.py
odoo/addons/stock_lot_production_date/models/stock_lot.py
odoo/addons/stock_lot_production_date/readme/CONTRIBUTORS.rst
odoo/addons/stock_lot_production_date/readme/CREDITS.rst
odoo/addons/stock_lot_production_date/readme/DESCRIPTION.rst
odoo/addons/stock_lot_production_date/readme/USAGE.rst
odoo/addons/stock_lot_production_date/static/description/icon.png
odoo/addons/stock_lot_production_date/static/description/index.html
odoo/addons/stock_lot_production_date/static/description/lot.png
odoo/addons/stock_lot_production_date/views/stock_lot.xml
odoo14_addon_stock_lot_production_date-14.0.1.0.1.dev10.dist-info/METADATA
odoo14_addon_stock_lot_production_date-14.0.1.0.1.dev10.dist-info/WHEEL
odoo14_addon_stock_lot_production_date-14.0.1.0.1.dev10.dist-info/top_level.txt
odoo14_addon_stock_lot_production_date-14.0.1.0.1.dev10.dist-info/RECORD
